django_extensions/__init__.py
django_extensions/fields.py
django_extensions/middlewares.py
django_extensions/version.py
django_extension_tools-0.0.2.dist-info/LICENSE
django_extension_tools-0.0.2.dist-info/METADATA
django_extension_tools-0.0.2.dist-info/WHEEL
django_extension_tools-0.0.2.dist-info/top_level.txt
django_extension_tools-0.0.2.dist-info/RECORD
