Metadata-Version: 2.1
Name: django-extension-tools
Version: 0.0.2
Summary: Django extention tools.
Home-page: https://github.com/yutayamazaki/django-extensions
Author: Yuta Yamazaki
Author-email: yu.yamazakii@gmail.com
Maintainer: Yuta Yamazaki
Maintainer-email: yu.yamazakii@gmail.com
License: MIT
Keywords: django,djangorestframework
Platform: UNKNOWN
Requires-Dist: django
